MANIFEST.in
README.rst
requirements.txt
setup.py
lisa/__init__.py
lisa/plugins/__init__.py
lisa/plugins/UnitTest/__init__.py
lisa/plugins/UnitTest/unittest.json
lisa/plugins/UnitTest/lang/fr/LC_MESSAGES/unittest.mo
lisa/plugins/UnitTest/lang/fr/LC_MESSAGES/unittest.po
lisa/plugins/UnitTest/modules/__init__.py
lisa/plugins/UnitTest/modules/unittest.py
lisa/plugins/UnitTest/test/__init__.py
lisa/plugins/UnitTest/test/chat_test.py
lisa/plugins/UnitTest/web/__init__.py
lisa/plugins/UnitTest/web/api.py
lisa/plugins/UnitTest/web/models.py
lisa/plugins/UnitTest/web/tests.py
lisa/plugins/UnitTest/web/urls.py
lisa/plugins/UnitTest/web/views.py
lisa_plugin_UnitTest.egg-info/PKG-INFO
lisa_plugin_UnitTest.egg-info/SOURCES.txt
lisa_plugin_UnitTest.egg-info/dependency_links.txt
lisa_plugin_UnitTest.egg-info/namespace_packages.txt
lisa_plugin_UnitTest.egg-info/requires.txt
lisa_plugin_UnitTest.egg-info/top_level.txt